EyeOfThePython/Pytrace_EyeOfThePython.py
EyeOfThePython/__init__.py
Pytrace_EyeOfThePython-0.0.3.dist-info/LICENSE
Pytrace_EyeOfThePython-0.0.3.dist-info/METADATA
Pytrace_EyeOfThePython-0.0.3.dist-info/WHEEL
Pytrace_EyeOfThePython-0.0.3.dist-info/top_level.txt
Pytrace_EyeOfThePython-0.0.3.dist-info/RECORD
